flexcpi/__init__.py
flexcpi/toolkit.py
flexcpi/data/bls_cpi_weights_table1.csv
flexcpi/data/bls_cpi_weights_table2.csv
flexcpi/data/cu.area.txt
flexcpi/data/cu.item.txt
flexcpi/data/cu.series.txt
flexcpi-0.1.2.dist-info/licenses/LICENSE
flexcpi-0.1.2.dist-info/METADATA
flexcpi-0.1.2.dist-info/WHEEL
flexcpi-0.1.2.dist-info/top_level.txt
flexcpi-0.1.2.dist-info/RECORD
