Metadata-Version: 2.4
Name: flexcpi
Version: 0.1.2
Summary: Build and analyze custom CPI baskets using BLS data
Author: Rory G Quinlan
Requires-Python: >=3.8
License-File: LICENSE
Requires-Dist: pandas>=1.3
Requires-Dist: matplotlib>=3.5
Requires-Dist: requests>=2.26
Requires-Dist: statsmodels>=0.13
Requires-Dist: importlib-resources>=5.4; python_version < "3.9"
Dynamic: license-file
